sql_cli/__init__.py
sql_cli/__main__.py
sql_cli/astro/__init__.py
sql_cli/astro/command.py
sql_cli/astro/group.py
sql_cli/astro/utils.py
sql_cli/cli/__init__.py
sql_cli/cli/config.py
sql_cli/cli/utils.py
sql_cli/configuration.py
sql_cli/connections.py
sql_cli/constants.py
sql_cli/dag_generator.py
sql_cli/dag_renderer.py
sql_cli/dag_runner.py
sql_cli/exceptions.py
sql_cli/include/base/.airflow/dags/.gitkeep
sql_cli/include/base/.airflow/dags/include/.gitkeep
sql_cli/include/base/.airflow/default/.gitkeep
sql_cli/include/base/.airflow/dev/.gitkeep
sql_cli/include/base/.env
sql_cli/include/base/config/default/configuration.yml
sql_cli/include/base/config/default/configuration.yml.example
sql_cli/include/base/config/dev/configuration.yml
sql_cli/include/base/config/global.yml
sql_cli/include/base/data/imdb.db
sql_cli/include/base/data/retail.db
sql_cli/include/base/workflows/example_basic_transform/top_animations.sql
sql_cli/include/base/workflows/example_deploy/orders.yaml
sql_cli/include/base/workflows/example_deploy/subset.sql
sql_cli/include/base/workflows/example_deploy/workflow.yml
sql_cli/include/base/workflows/example_load_file/load_imdb_movies.yaml
sql_cli/include/base/workflows/example_load_file/transform_imdb_movies.sql
sql_cli/include/base/workflows/example_templating/filtered_orders.sql
sql_cli/include/base/workflows/example_templating/joint_orders_customers.sql
sql_cli/macros/build_dag.py.jinja2
sql_cli/macros/load_file.py.jinja2
sql_cli/macros/transform_file.py.jinja2
sql_cli/operators/__init__.py
sql_cli/operators/load_file.py
sql_cli/operators/transform.py
sql_cli/project.py
sql_cli/settings.py
sql_cli/templates/gen_tasks_dag.py.jinja2
sql_cli/templates/render_dag.py.jinja2
sql_cli/utils/__init__.py
sql_cli/utils/airflow.py
sql_cli/utils/jinja.py
sql_cli/utils/rich.py
sql_cli/workflow_directory_parser.py
astro_sql_cli-0.4.1.dist-info/LICENSE
astro_sql_cli-0.4.1.dist-info/WHEEL
astro_sql_cli-0.4.1.dist-info/entry_points.txt
astro_sql_cli-0.4.1.dist-info/METADATA
astro_sql_cli-0.4.1.dist-info/RECORD
